arpa/exceptions.py
arpa/__init__.py
arpa/arpa.py
arpa/parsers/quick.py
arpa/parsers/base.py
arpa/parsers/__init__.py
arpa/models/base.py
arpa/models/simple.py
arpa/models/__init__.py
arpa-0.1.0a6.dist-info/WHEEL
arpa-0.1.0a6.dist-info/top_level.txt
arpa-0.1.0a6.dist-info/metadata.json
arpa-0.1.0a6.dist-info/DESCRIPTION.rst
arpa-0.1.0a6.dist-info/zip-safe
arpa-0.1.0a6.dist-info/pbr.json
arpa-0.1.0a6.dist-info/RECORD
arpa-0.1.0a6.dist-info/METADATA
